multiversx_sdk_rust_contract_builder/__init__.py
multiversx_sdk_rust_contract_builder/build_outcome.py
multiversx_sdk_rust_contract_builder/builder.py
multiversx_sdk_rust_contract_builder/builder_test.py
multiversx_sdk_rust_contract_builder/cargo_toml.py
multiversx_sdk_rust_contract_builder/codehash.py
multiversx_sdk_rust_contract_builder/constants.py
multiversx_sdk_rust_contract_builder/errors.py
multiversx_sdk_rust_contract_builder/filesystem.py
multiversx_sdk_rust_contract_builder/main.py
multiversx_sdk_rust_contract_builder/packaged_source_code.py
multiversx_sdk_rust_contract_builder/source_code.py
multiversx_sdk_rust_contract_builder/wabt.py
multiversx_sdk_rust_contract_builder-4.1.1.dist-info/METADATA
multiversx_sdk_rust_contract_builder-4.1.1.dist-info/WHEEL
multiversx_sdk_rust_contract_builder-4.1.1.dist-info/licenses/LICENSE
multiversx_sdk_rust_contract_builder-4.1.1.dist-info/RECORD
