Metadata-Version: 2.1
Name: multiversx-sdk-rust-contract-builder
Version: 4.1.1
Summary: MultiversX: utility package for building Rust contracts (reproducible builds).
Project-URL: Homepage, https://github.com/multiversx/mx-sdk-build-contract
Author: MultiversX
License-Expression: MIT
License-File: LICENSE
Classifier: License :: OSI Approved :: MIT License
Classifier: Operating System :: OS Independent
Classifier: Programming Language :: Python :: 3
Requires-Python: >=3.8
